{
  "id": "value_proposition",
  "type": "SharedSlice",
  "name": "ValueProposition",
  "description": "ValueProposition",
  "variations": [
    {
      "id": "default",
      "name": "TwoColumns",
      "docURL": "...",
      "version": "initial",
      "description": "Default",
      "imageUrl": "",
      "primary": {
        "theme": {
          "type": "Select",
          "config": {
            "label": "Theme",
            "placeholder": "Slide theme color",
            "options": [
              "slider theme",
              "white",
              "orange",
              "pink",
              "green",
              "purple",
              "blue"
            ],
            "default_value": "slider theme"
          }
        },
        "eyebrow": {
          "type": "Text",
          "config": {
            "label": "Eyebrow",
            "placeholder": ""
          }
        },
        "title": {
          "type": "StructuredText",
          "config": {
            "label": "Title",
            "placeholder": "",
            "allowTargetBlank": true,
            "single": "heading2,strong,em,hyperlink",
            "labels": [
              "highlight",
              "Company Name"
            ]
          }
        },
        "description": {
          "type": "StructuredText",
          "config": {
            "label": "Description",
            "placeholder": "",
            "allowTargetBlank": true,
            "multi": "paragraph,strong,em,hyperlink,list-item,o-list-item",
            "labels": [
              "highlight",
              "Company Name"
            ]
          }
        },
        "image": {
          "type": "Image",
          "config": {
            "label": "Image",
            "constraint": {
              "width": 695,
              "height": 705
            },
            "thumbnails": []
          }
        },
        "image_border": {
          "type": "Boolean",
          "config": {
            "label": "Image border",
            "placeholder_false": "no border",
            "placeholder_true": "border",
            "default_value": true
          }
        }
      },
      "items": {}
    },
    {
      "id": "twoColumnsWithLogos",
      "name": "Two Columns With Logos",
      "docURL": "...",
      "version": "initial",
      "description": "Default",
      "imageUrl": "",
      "primary": {
        "theme": {
          "type": "Select",
          "config": {
            "label": "Theme",
            "placeholder": "Slide theme color",
            "options": [
              "slider theme",
              "white",
              "orange",
              "pink",
              "green",
              "purple",
              "blue"
            ],
            "default_value": "slider theme"
          }
        },
        "eyebrow": {
          "type": "Text",
          "config": {
            "label": "Eyebrow",
            "placeholder": ""
          }
        },
        "title": {
          "type": "StructuredText",
          "config": {
            "label": "Title",
            "placeholder": "",
            "allowTargetBlank": true,
            "single": "heading2,strong,em,hyperlink",
            "labels": [
              "highlight",
              "Company Name"
            ]
          }
        },
        "description": {
          "type": "StructuredText",
          "config": {
            "label": "Description",
            "placeholder": "",
            "allowTargetBlank": true,
            "multi": "paragraph,strong,em,hyperlink,list-item,o-list-item",
            "labels": [
              "highlight",
              "Company Name"
            ]
          }
        },
        "image": {
          "type": "Image",
          "config": {
            "label": "Image",
            "constraint": {
              "width": 664,
              "height": 705
            },
            "thumbnails": []
          }
        },
        "image_border": {
          "type": "Boolean",
          "config": {
            "label": "Image border",
            "placeholder_false": "no border",
            "placeholder_true": "border",
            "default_value": true
          }
        },
        "logos": {
          "type": "Group",
          "config": {
            "label": "Logos",
            "repeat": true,
            "fields": {
              "logo": {
                "type": "Image",
                "config": {
                  "label": "Logo",
                  "constraint": {
                    "height": 80
                  },
                  "thumbnails": []
                }
              }
            }
          }
        }
      },
      "items": {}
    },
    {
      "id": "withList",
      "name": "With List",
      "docURL": "...",
      "version": "initial",
      "description": "Default",
      "imageUrl": "",
      "primary": {
        "theme": {
          "type": "Select",
          "config": {
            "label": "Theme",
            "placeholder": "Slide theme color",
            "options": [
              "slider theme",
              "white",
              "orange",
              "pink",
              "green",
              "purple",
              "blue"
            ],
            "default_value": "slider theme"
          }
        },
        "eyebrow": {
          "type": "Text",
          "config": {
            "label": "Eyebrow",
            "placeholder": ""
          }
        },
        "title": {
          "type": "StructuredText",
          "config": {
            "label": "Title",
            "placeholder": "",
            "allowTargetBlank": true,
            "single": "heading2,strong,em,hyperlink",
            "labels": [
              "highlight",
              "Company Name"
            ]
          }
        },
        "description": {
          "type": "StructuredText",
          "config": {
            "label": "Description",
            "placeholder": "",
            "allowTargetBlank": true,
            "multi": "paragraph,em,strong",
            "labels": [
              "highlight",
              "Company Name"
            ]
          }
        },
        "list": {
          "type": "Group",
          "config": {
            "label": "List",
            "repeat": true,
            "fields": {
              "list_item": {
                "type": "StructuredText",
                "config": {
                  "label": "List item",
                  "placeholder": "",
                  "allowTargetBlank": true,
                  "single": "paragraph,strong,em,hyperlink",
                  "labels": [
                    "highlight",
                    "Company Name"
                  ]
                }
              },
              "list_icon": {
                "type": "Image",
                "config": {
                  "label": "List icon",
                  "constraint": {
                    "width": 80,
                    "height": 80
                  },
                  "thumbnails": []
                }
              }
            }
          }
        }
      },
      "items": {}
    }
  ]
}